Vinted_OSINT.py
Vinted_OSINT-1.1.dist-info/LICENSE
Vinted_OSINT-1.1.dist-info/METADATA
Vinted_OSINT-1.1.dist-info/WHEEL
Vinted_OSINT-1.1.dist-info/entry_points.txt
Vinted_OSINT-1.1.dist-info/top_level.txt
Vinted_OSINT-1.1.dist-info/RECORD
