Metadata-Version: 2.1
Name: Vinted_OSINT
Version: 1.1
Summary: An OSINT tool for Vinted.com
Home-page: https://github.com/EchterAlsFake/Vinted_OSINT
Author: Johannes Habel
Author-email: EchterAlsFake@proton.me
License: GPLv3
Classifier: License :: OSI Approved :: GNU Lesser General Public License v3 (LGPLv3)
Classifier: Programming Language :: Python
License-File: LICENSE
Requires-Dist: requests
Requires-Dist: colorama
Requires-Dist: fake_useragent
Requires-Dist: prettytable
